data_quality_sdk/__init__.py
data_quality_sdk/config.py
data_quality_sdk/main.py
data_quality_sdk/client/__init__.py
data_quality_sdk/client/alation_client.py
data_quality_sdk/client/query_client.py
data_quality_sdk/datasource/__init__.py
data_quality_sdk/datasource/config_generator.py
data_quality_sdk/datasource/soda_runner.py
data_quality_sdk/utils/__init__.py
data_quality_sdk/utils/exceptions.py
data_quality_sdk/utils/logging.py
alation_data_quality_sdk-1.0.5.dist-info/METADATA
alation_data_quality_sdk-1.0.5.dist-info/WHEEL
alation_data_quality_sdk-1.0.5.dist-info/entry_points.txt
alation_data_quality_sdk-1.0.5.dist-info/licenses/LICENSE
alation_data_quality_sdk-1.0.5.dist-info/RECORD
