Metadata-Version: 2.4
Name: alation-data-quality-sdk
Version: 1.0.5
Summary: Production-ready SDK for running Alation data quality checks using Soda Core
Project-URL: Homepage, https://pypi.org/project/alation-data-quality-sdk/
Project-URL: Documentation, https://www.alation.com/docs/en/latest/
Author-email: Alation Engineering <support@alation.com>
Maintainer-email: Alation Engineering <support@alation.com>
License: Apache License
License-File: LICENSE
Keywords: Airflow,Alation,Data Pipeline,Data Quality,Soda Core
Classifier: Development Status :: 4 - Beta
Classifier: Intended Audience :: Developers
Classifier: License :: OSI Approved :: Apache Software License
Classifier: Operating System :: OS Independent
Classifier: Programming Language :: Python :: 3
Classifier: Programming Language :: Python :: 3.9
Classifier: Programming Language :: Python :: 3.10
Classifier: Programming Language :: Python :: 3.11
Classifier: Programming Language :: Python :: 3.12
Classifier: Topic :: Database
Classifier: Topic :: Software Development :: Quality Assurance
Requires-Python: >=3.9
Requires-Dist: grpcio>=1.40.0
Requires-Dist: protobuf>=3.19.0
Requires-Dist: pyyaml>=6.0
Requires-Dist: queryservice-client==0.1.0+53
Requires-Dist: requests>=2.25.0
Requires-Dist: soda-core-bigquery==3.4.4
Requires-Dist: soda-core-oracle==3.4.4
Requires-Dist: soda-core-postgres==3.4.4
Requires-Dist: soda-core-redshift==3.4.4
Requires-Dist: soda-core-snowflake==3.4.4
Requires-Dist: soda-core-spark-df==3.4.4
Requires-Dist: soda-core-spark[databricks]==3.4.4
Requires-Dist: soda-core-sqlserver==3.4.4
Requires-Dist: soda-core==3.4.4+131
Provides-Extra: dev
Requires-Dist: black>=22.0.0; extra == 'dev'
Requires-Dist: flake8>=4.0.0; extra == 'dev'
Requires-Dist: mypy>=0.910; extra == 'dev'
Requires-Dist: pre-commit>=3.0.0; extra == 'dev'
Requires-Dist: pytest-cov>=3.0.0; extra == 'dev'
Requires-Dist: pytest-mock>=3.6.0; extra == 'dev'
Requires-Dist: pytest>=6.0.0; extra == 'dev'
Requires-Dist: requests-mock>=1.9.0; extra == 'dev'
